wujian/__init__.py
wujian-1.0.1.dist-info/LICENSE
wujian-1.0.1.dist-info/METADATA
wujian-1.0.1.dist-info/WHEEL
wujian-1.0.1.dist-info/top_level.txt
wujian-1.0.1.dist-info/RECORD
